template_generator/__init__.py
template_generator/aigc_input.py
template_generator/binary.py
template_generator/convertor.py
template_generator/ffmpeg.py
template_generator/main.py
template_generator/of_to_skymedia.py
template_generator/template.py
template_generator/template_service.py
template_generator/template_test.py
template_generator/bin/__init__.py
template_generator/bin/print_md5.py
template_generator/test/__init__.py
template_generator/test/tp_2023112102.zip.py
p_template_generator_old-0.2.44.dist-info/LICENSE
p_template_generator_old-0.2.44.dist-info/METADATA
p_template_generator_old-0.2.44.dist-info/WHEEL
p_template_generator_old-0.2.44.dist-info/entry_points.txt
p_template_generator_old-0.2.44.dist-info/top_level.txt
p_template_generator_old-0.2.44.dist-info/RECORD
