Metadata-Version: 2.2
Name: p-template-generator-old
Version: 0.2.44
Summary: temple tools
Author: pengjun
Author-email: mr_lonely@foxmail.com
Classifier: Programming Language :: Python :: 3
Classifier: License :: OSI Approved :: MIT License
Classifier: Operating System :: OS Independent
Requires-Python: >=3.7
License-File: LICENSE
Requires-Dist: requests
Requires-Dist: Image
Requires-Dist: protobuf
Requires-Dist: imagesize
Requires-Dist: urlparser
Requires-Dist: Pillow
Requires-Dist: p-template-res
Dynamic: author
Dynamic: author-email
Dynamic: classifier
Dynamic: description
Dynamic: description-content-type
Dynamic: requires-dist
Dynamic: requires-python
Dynamic: summary
